newchanic/__init__.py
newchanic/graphical_engine.py
newchanic/physics.py
newchanic/utils.py
newchanic-1.0.2.dist-info/LICENSE
newchanic-1.0.2.dist-info/METADATA
newchanic-1.0.2.dist-info/WHEEL
newchanic-1.0.2.dist-info/top_level.txt
newchanic-1.0.2.dist-info/RECORD
