Metadata-Version: 2.1
Name: newchanic
Version: 1.0.2
Summary: Simulate a universe powered by Newton's mechanic
Home-page: https://github.com/Louis-Saglio/newchanic
Author: Louis Saglio
Author-email: louis.saglio@ynov.com
License: MIT
Platform: UNKNOWN
Classifier: License :: OSI Approved :: MIT License
Classifier: Programming Language :: Python :: 3
Classifier: Programming Language :: Python :: 3.7
Requires-Dist: pygame
